README.rst
setup.cfg
setup.py
kiefer/__init__.py
kiefer/auth.py
kiefer/client.py
kiefer/util.py
kiefer.egg-info/PKG-INFO
kiefer.egg-info/SOURCES.txt
kiefer.egg-info/dependency_links.txt
kiefer.egg-info/requires.txt
kiefer.egg-info/top_level.txt