Metadata-Version: 1.0
Name: kiefer
Version: 0.2
Summary: A Python wrapper for the Jawbone UP API.
Home-page: https://github.com/andygoldschmidt/kiefer
Author: Andy Goldschmidt
Author-email: andy@abby.io
License: MIT
Platform: UNKNOWN
